seedos_langchain/__init__.py
seedos_langchain/memory.py
tests/__init__.py
tests/test_integration.py
tests/test_memory.py
seedos_langchain-0.2.0.dist-info/METADATA
seedos_langchain-0.2.0.dist-info/WHEEL
seedos_langchain-0.2.0.dist-info/top_level.txt
seedos_langchain-0.2.0.dist-info/RECORD
